mahiru/twitch/__init__.py
mahiru/twitch/eventsub.py
mahiru/twitch/module.py
mahiru_twitch-0.0.3.dist-info/METADATA
mahiru_twitch-0.0.3.dist-info/WHEEL
mahiru_twitch-0.0.3.dist-info/top_level.txt
mahiru_twitch-0.0.3.dist-info/RECORD
