Metadata-Version: 2.1
Name: mahiru-twitch
Version: 0.0.3
Summary: Twitch module for Mahiru
Home-page: https://gitlab.com/henny022/mahiru/twitch
Author: Henny022
Author-email: hen.geheim22@gmail.com
License: Unlicense
Platform: UNKNOWN
Classifier: License :: OSI Approved :: The Unlicense (Unlicense)
Classifier: Programming Language :: Python :: 3
Classifier: Programming Language :: Python :: 3.7
Requires-Python: >=3.7
Requires-Dist: mahiru-core
Requires-Dist: aiohttp
Requires-Dist: twitch-ws-irc
Requires-Dist: twitch-helix
